[
    {
        "id": "f000001",
        "sentence": "宮沢賢治　作",
        "sentence_with_furigana": "宮沢賢治　作"
    },
    {
        "id": "f000002",
        "sentence": "クねずみ",
        "sentence_with_furigana": "クねずみ"
    },
    {
        "id": "f000003",
        "sentence": "クという名前のねずみがありました。",
        "sentence_with_furigana": "クという名前のねずみがありました。"
    },
    {
        "id": "f000004",
        "sentence": "たいへん高慢でそれにそねみ深くって、",
        "sentence_with_furigana": "たいへん高慢でそれにそねみ深くって、"
    },
    {
        "id": "f000005",
        "sentence": "自分をねずみの仲間の一番の学者と思っていました。",
        "sentence_with_furigana": "自分をねずみの仲間の一番の学者と思っていました。"
    },
    {
        "id": "f000006",
        "sentence": "ほかのねずみが何か生意気なことを言うとエヘンエヘンと言うのが癖でした。",
        "sentence_with_furigana": "ほかのねずみが何か生意気なことを言うとエヘンエヘンと言うのが癖でした。"
    },
    {
        "id": "f000007",
        "sentence": "クねずみのうちへ、",
        "sentence_with_furigana": "クねずみのうちへ、"
    },
    {
        "id": "f000008",
        "sentence": "ある日、",
        "sentence_with_furigana": "ある日、"
    },
    {
        "id": "f000009",
        "sentence": "友だちのタねずみがやって来ました。",
        "sentence_with_furigana": "友だちのタねずみがやって来ました。"
    },
    {
        "id": "f000010",
        "sentence": "さてタねずみはクねずみに言いました。",
        "sentence_with_furigana": "さてタねずみはクねずみに言いました。"
    },
    {
        "id": "f000011",
        "sentence": "「今日は、",
        "sentence_with_furigana": "「 今日[こんにち]は、"
    },
    {
        "id": "f000012",
        "sentence": "クさん。",
        "sentence_with_furigana": "クさん。"
    },
    {
        "id": "f000013",
        "sentence": "いいお天気です。」",
        "sentence_with_furigana": "いいお天気です。」"
    },
    {
        "id": "f000014",
        "sentence": "「いいお天気です。",
        "sentence_with_furigana": "「いいお天気です。"
    },
    {
        "id": "f000015",
        "sentence": "何かいいものを見つけましたか。」",
        "sentence_with_furigana": "何かいいものを見つけましたか。」"
    },
    {
        "id": "f000016",
        "sentence": "「いいえ。",
        "sentence_with_furigana": "「いいえ。"
    },
    {
        "id": "f000017",
        "sentence": "どうも不景気ですね。",
        "sentence_with_furigana": "どうも不景気ですね。"
    },
    {
        "id": "f000018",
        "sentence": "どうでしょう。",
        "sentence_with_furigana": "どうでしょう。"
    },
    {
        "id": "f000019",
        "sentence": "これからの景気は。」",
        "sentence_with_furigana": "これからの景気は。」"
    },
    {
        "id": "f000020",
        "sentence": "「さあ、",
        "sentence_with_furigana": "「さあ、"
    },
    {
        "id": "f000021",
        "sentence": "あなたはどう思いますか。」",
        "sentence_with_furigana": "あなたはどう思いますか。」"
    },
    {
        "id": "f000022",
        "sentence": "「そうですね。",
        "sentence_with_furigana": "「そうですね。"
    },
    {
        "id": "f000023",
        "sentence": "しかしだんだんよくなるのじゃないでしょうか。",
        "sentence_with_furigana": "しかしだんだんよくなるのじゃないでしょうか。"
    },
    {
        "id": "f000024",
        "sentence": "オウベイのキンユウはしだいにヒッパクをテイしたそう……。」",
        "sentence_with_furigana": "オウベイのキンユウはしだいにヒッパクをテイしたそう……。」"
    },
    {
        "id": "f000025",
        "sentence": "「エヘン、",
        "sentence_with_furigana": "「エヘン、"
    },
    {
        "id": "f000026",
        "sentence": "エヘン。",
        "sentence_with_furigana": "エヘン。"
    },
    {
        "id": "f000027",
        "sentence": "」いきなりクねずみが大きなせきばらいをしましたので、",
        "sentence_with_furigana": "」いきなりクねずみが大きなせきばらいをしましたので、"
    },
    {
        "id": "f000028",
        "sentence": "タねずみはびっくりして飛びあがりました。",
        "sentence_with_furigana": "タねずみはびっくりして飛びあがりました。"
    },
    {
        "id": "f000029",
        "sentence": "クねずみは横を向いたまま、",
        "sentence_with_furigana": "クねずみは横を向いたまま、"
    },
    {
        "id": "f000030",
        "sentence": "ひげを一つぴんとひねって、",
        "sentence_with_furigana": "ひげを一つぴんとひねって、"
    },
    {
        "id": "f000031",
        "sentence": "それから口の中で、",
        "sentence_with_furigana": "それから口の中で、"
    },
    {
        "id": "f000032",
        "sentence": "「ヘイ、",
        "sentence_with_furigana": "「ヘイ、"
    },
    {
        "id": "f000033",
        "sentence": "それから。",
        "sentence_with_furigana": "それから。"
    },
    {
        "id": "f000034",
        "sentence": "」と言いました。",
        "sentence_with_furigana": "」と言いました。"
    },
    {
        "id": "f000035",
        "sentence": "タねずみはやっと安心してまたおひざに手を置いてすわりました。",
        "sentence_with_furigana": "タねずみはやっと安心してまたおひざに手を置いてすわりました。"
    },
    {
        "id": "f000036",
        "sentence": "クねずみもやっとまっすぐを向いて言いました。",
        "sentence_with_furigana": "クねずみもやっとまっすぐを向いて言いました。"
    },
    {
        "id": "f000037",
        "sentence": "「先ころの地震にはおどろきましたね。」",
        "sentence_with_furigana": "「 先[せん]ころの地震にはおどろきましたね。」"
    },
    {
        "id": "f000038",
        "sentence": "「全くです。」",
        "sentence_with_furigana": "「全くです。」"
    },
    {
        "id": "f000039",
        "sentence": "「あんな大きいのは私もはじめてですよ。」",
        "sentence_with_furigana": "「あんな大きいのは私もはじめてですよ。」"
    },
    {
        "id": "f000040",
        "sentence": "「ええ、",
        "sentence_with_furigana": "「ええ、"
    },
    {
        "id": "f000041",
        "sentence": "ジョウカドウでしたねえ。",
        "sentence_with_furigana": "ジョウカドウでしたねえ。"
    },
    {
        "id": "f000042",
        "sentence": "シンゲンはなんでもトウケイ四十二度二分ナンイ……。」",
        "sentence_with_furigana": "シンゲンはなんでもトウケイ四十二度二分ナンイ……。」"
    },
    {
        "id": "f000043",
        "sentence": "「エヘン、",
        "sentence_with_furigana": "「エヘン、"
    },
    {
        "id": "f000044",
        "sentence": "エヘン。」",
        "sentence_with_furigana": "エヘン。」"
    },
    {
        "id": "f000045",
        "sentence": "クねずみはまたどなりました。",
        "sentence_with_furigana": "クねずみはまたどなりました。"
    },
    {
        "id": "f000046",
        "sentence": "タねずみはまた面くらいましたが、",
        "sentence_with_furigana": "タねずみはまた 面[めん]くらいましたが、"
    },
    {
        "id": "f000047",
        "sentence": "さっきほどではありませんでした。",
        "sentence_with_furigana": "さっきほどではありませんでした。"
    },
    {
        "id": "f000048",
        "sentence": "クねずみはやっと気を直して言いました。",
        "sentence_with_furigana": "クねずみはやっと気を直して言いました。"
    },
    {
        "id": "f000049",
        "sentence": "「天気もよくなりましたね。",
        "sentence_with_furigana": "「天気もよくなりましたね。"
    },
    {
        "id": "f000050",
        "sentence": "あなたは何かうまい仕掛けをしておきましたか。」",
        "sentence_with_furigana": "あなたは何かうまい仕掛けをしておきましたか。」"
    },
    {
        "id": "f000051",
        "sentence": "「いいえ、",
        "sentence_with_furigana": "「いいえ、"
    },
    {
        "id": "f000052",
        "sentence": "なんにもしておきません。",
        "sentence_with_furigana": "なんにもしておきません。"
    },
    {
        "id": "f000053",
        "sentence": "しかし、",
        "sentence_with_furigana": "しかし、"
    },
    {
        "id": "f000054",
        "sentence": "今度天気が長くつづいたら、",
        "sentence_with_furigana": "今度天気が長くつづいたら、"
    },
    {
        "id": "f000055",
        "sentence": "私は少し畑の方へ出てみようと思うんです。」",
        "sentence_with_furigana": "私は少し畑の方へ出てみようと思うんです。」"
    },
    {
        "id": "f000056",
        "sentence": "「畑には何かいいことがありますか。」",
        "sentence_with_furigana": "「畑には何かいいことがありますか。」"
    },
    {
        "id": "f000057",
        "sentence": "「秋ですからとにかく何かこぼれているだろうと思います。",
        "sentence_with_furigana": "「秋ですからとにかく何かこぼれているだろうと思います。"
    },
    {
        "id": "f000058",
        "sentence": "天気さえよければいいのですがね。」",
        "sentence_with_furigana": "天気さえよければいいのですがね。」"
    },
    {
        "id": "f000059",
        "sentence": "「どうでしょう。",
        "sentence_with_furigana": "「どうでしょう。"
    },
    {
        "id": "f000060",
        "sentence": "天気はいいでしょうか。」",
        "sentence_with_furigana": "天気はいいでしょうか。」"
    },
    {
        "id": "f000061",
        "sentence": "「そうですね、",
        "sentence_with_furigana": "「そうですね、"
    },
    {
        "id": "f000062",
        "sentence": "新聞に出ていましたが、",
        "sentence_with_furigana": "新聞に出ていましたが、"
    },
    {
        "id": "f000063",
        "sentence": "オキナワレットウにハッセイしたテイキアツは次第にホクホクセイのほうへシンコウ……。」",
        "sentence_with_furigana": "オキナワレットウにハッセイしたテイキアツは次第にホクホクセイのほうへシンコウ……。」"
    },
    {
        "id": "f000064",
        "sentence": "「エヘン、",
        "sentence_with_furigana": "「エヘン、"
    },
    {
        "id": "f000065",
        "sentence": "エヘン。",
        "sentence_with_furigana": "エヘン。"
    },
    {
        "id": "f000066",
        "sentence": "」クねずみはまたいやなせきばらいをやりましたので、",
        "sentence_with_furigana": "」クねずみはまたいやなせきばらいをやりましたので、"
    },
    {
        "id": "f000067",
        "sentence": "タねずみはこんどというこんどはすっかりびっくりして半分立ちあがって、",
        "sentence_with_furigana": "タねずみはこんどというこんどはすっかりびっくりして半分立ちあがって、"
    },
    {
        "id": "f000068",
        "sentence": "ぶるぶるふるえて目をパチパチさせて、",
        "sentence_with_furigana": "ぶるぶるふるえて目をパチパチさせて、"
    },
    {
        "id": "f000069",
        "sentence": "黙りこんでしまいました。",
        "sentence_with_furigana": "黙りこんでしまいました。"
    },
    {
        "id": "f000070",
        "sentence": "クねずみは横の方を向いて、",
        "sentence_with_furigana": "クねずみは横の方を向いて、"
    },
    {
        "id": "f000071",
        "sentence": "おひげをひっぱりながら、",
        "sentence_with_furigana": "おひげをひっぱりながら、"
    },
    {
        "id": "f000072",
        "sentence": "横目でタねずみの顔を見ていましたが、",
        "sentence_with_furigana": "横目でタねずみの顔を見ていましたが、"
    },
    {
        "id": "f000073",
        "sentence": "ずうっとしばらくたってから、",
        "sentence_with_furigana": "ずうっとしばらくたってから、"
    },
    {
        "id": "f000074",
        "sentence": "あらんかぎり声をひくくして、",
        "sentence_with_furigana": "あらんかぎり声をひくくして、"
    },
    {
        "id": "f000075",
        "sentence": "「へい。",
        "sentence_with_furigana": "「へい。"
    },
    {
        "id": "f000076",
        "sentence": "そして。",
        "sentence_with_furigana": "そして。"
    },
    {
        "id": "f000077",
        "sentence": "」と言いました。",
        "sentence_with_furigana": "」と言いました。"
    },
    {
        "id": "f000078",
        "sentence": "ところがタねずみはもうすっかりこわくなって物が言えませんでしたから、",
        "sentence_with_furigana": "ところがタねずみはもうすっかりこわくなって物が言えませんでしたから、"
    },
    {
        "id": "f000079",
        "sentence": "にわかに一つていねいにおじぎをしました。",
        "sentence_with_furigana": "にわかに一つていねいにおじぎをしました。"
    },
    {
        "id": "f000080",
        "sentence": "そしてまるで細いかすれた声で、",
        "sentence_with_furigana": "そしてまるで細いかすれた声で、"
    },
    {
        "id": "f000081",
        "sentence": "「さよなら。",
        "sentence_with_furigana": "「さよなら。"
    },
    {
        "id": "f000082",
        "sentence": "」と言ってクねずみのおうちを出て行きました。",
        "sentence_with_furigana": "」と言ってクねずみのおうちを出て行きました。"
    },
    {
        "id": "f000083",
        "sentence": "クねずみは、",
        "sentence_with_furigana": "クねずみは、"
    },
    {
        "id": "f000084",
        "sentence": "そこであおむけにねころんで、",
        "sentence_with_furigana": "そこであおむけにねころんで、"
    },
    {
        "id": "f000085",
        "sentence": "「ねずみ競争新聞」を手にとってひろげながら、",
        "sentence_with_furigana": "「ねずみ競争新聞」を手にとってひろげながら、"
    },
    {
        "id": "f000086",
        "sentence": "「ヘッ。",
        "sentence_with_furigana": "「ヘッ。"
    },
    {
        "id": "f000087",
        "sentence": "タなどはなってないんだ。",
        "sentence_with_furigana": "タなどはなってないんだ。"
    },
    {
        "id": "f000088",
        "sentence": "」とひとりごとを言いました。",
        "sentence_with_furigana": "」とひとりごとを言いました。"
    },
    {
        "id": "f000089",
        "sentence": "さて、",
        "sentence_with_furigana": "さて、"
    },
    {
        "id": "f000090",
        "sentence": "「ねずみ競争新聞」というのは実にいい新聞です。",
        "sentence_with_furigana": "「ねずみ競争新聞」というのは実にいい新聞です。"
    },
    {
        "id": "f000091",
        "sentence": "これを読むと、",
        "sentence_with_furigana": "これを読むと、"
    },
    {
        "id": "f000092",
        "sentence": "ねずみ仲間の競争のことはなんでもわかるのでした。",
        "sentence_with_furigana": "ねずみ仲間の競争のことはなんでもわかるのでした。"
    },
    {
        "id": "f000093",
        "sentence": "ペねずみが、",
        "sentence_with_furigana": "ペねずみが、"
    },
    {
        "id": "f000094",
        "sentence": "たくさんとうもろこしのつぶをぬすみためて、",
        "sentence_with_furigana": "たくさんとうもろこしのつぶをぬすみためて、"
    },
    {
        "id": "f000095",
        "sentence": "大砂糖持ちのパねずみと意地ばりの競争をしていることでも、",
        "sentence_with_furigana": "大砂糖持ちのパねずみと意地ばりの競争をしていることでも、"
    },
    {
        "id": "f000096",
        "sentence": "ハねずみヒねずみフねずみの三匹のむすめねずみが学問の競争をやって、",
        "sentence_with_furigana": "ハねずみヒねずみフねずみの三匹のむすめねずみが学問の競争をやって、"
    },
    {
        "id": "f000097",
        "sentence": "比例の問題まで来たとき、",
        "sentence_with_furigana": "比例の問題まで来たとき、"
    },
    {
        "id": "f000098",
        "sentence": "とうとう三匹とも頭がペチンと裂けたことでも、",
        "sentence_with_furigana": "とうとう三匹とも頭がペチンと裂けたことでも、"
    },
    {
        "id": "f000099",
        "sentence": "なんでもすっかり出ているのでした。",
        "sentence_with_furigana": "なんでもすっかり出ているのでした。"
    },
    {
        "id": "f000100",
        "sentence": "さあ、",
        "sentence_with_furigana": "さあ、"
    },
    {
        "id": "f000101",
        "sentence": "さあ、",
        "sentence_with_furigana": "さあ、"
    },
    {
        "id": "f000102",
        "sentence": "みなさん。",
        "sentence_with_furigana": "みなさん。"
    },
    {
        "id": "f000103",
        "sentence": "失礼ですが、",
        "sentence_with_furigana": "失礼ですが、"
    },
    {
        "id": "f000104",
        "sentence": "クねずみのきょうの新聞を読むのを、",
        "sentence_with_furigana": "クねずみのきょうの新聞を読むのを、"
    },
    {
        "id": "f000105",
        "sentence": "お聞きなさい。",
        "sentence_with_furigana": "お聞きなさい。"
    },
    {
        "id": "f000106",
        "sentence": "「ええと、",
        "sentence_with_furigana": "「ええと、"
    },
    {
        "id": "f000107",
        "sentence": "カマジン国の飛行機、",
        "sentence_with_furigana": "カマジン国の飛行機、"
    },
    {
        "id": "f000108",
        "sentence": "プハラを襲うと。",
        "sentence_with_furigana": "プハラを襲うと。"
    },
    {
        "id": "f000109",
        "sentence": "なるほどえらいね。",
        "sentence_with_furigana": "なるほどえらいね。"
    },
    {
        "id": "f000110",
        "sentence": "これはたいへんだ。",
        "sentence_with_furigana": "これはたいへんだ。"
    },
    {
        "id": "f000111",
        "sentence": "まあしかし、",
        "sentence_with_furigana": "まあしかし、"
    },
    {
        "id": "f000112",
        "sentence": "ここまでは来ないから大丈夫だ。",
        "sentence_with_furigana": "ここまでは来ないから大丈夫だ。"
    },
    {
        "id": "f000113",
        "sentence": "ええと、",
        "sentence_with_furigana": "ええと、"
    },
    {
        "id": "f000114",
        "sentence": "ツェねずみの行くえ不明。",
        "sentence_with_furigana": "ツェねずみの行くえ不明。"
    },
    {
        "id": "f000115",
        "sentence": "ツェねずみというのはあの意地わるだな。",
        "sentence_with_furigana": "ツェねずみというのはあの意地わるだな。"
    },
    {
        "id": "f000116",
        "sentence": "こいつはおもしろい。",
        "sentence_with_furigana": "こいつはおもしろい。"
    },
    {
        "id": "f000117",
        "sentence": "天井裏街一番地、",
        "sentence_with_furigana": "天井裏街一番地、"
    },
    {
        "id": "f000118",
        "sentence": "ツェ氏は昨夜行くえ不明となりたり。",
        "sentence_with_furigana": "ツェ氏は昨夜行くえ不明となりたり。"
    },
    {
        "id": "f000119",
        "sentence": "本社のいちはやく探知するところによればツェ氏は数日前よりはりがねせい、",
        "sentence_with_furigana": "本社のいちはやく探知するところによればツェ氏は数日前よりはりがねせい、"
    },
    {
        "id": "f000120",
        "sentence": "ねずみとり氏と交際を結びおりしが一昨夜に至りて両氏の間に多少感情の衝突ありたるもののごとし。",
        "sentence_with_furigana": "ねずみとり氏と交際を結びおりしが一昨夜に至りて両氏の間に多少感情の衝突ありたるもののごとし。"
    },
    {
        "id": "f000121",
        "sentence": "台所街四番地ネ氏の談によれば昨夜もツェ氏は、",
        "sentence_with_furigana": "台所街四番地ネ氏の談によれば昨夜もツェ氏は、"
    },
    {
        "id": "f000122",
        "sentence": "はりがねせい、",
        "sentence_with_furigana": "はりがねせい、"
    },
    {
        "id": "f000123",
        "sentence": "ねずみとり氏を訪問したるがごとし、",
        "sentence_with_furigana": "ねずみとり氏を訪問したるがごとし、"
    },
    {
        "id": "f000124",
        "sentence": "と。",
        "sentence_with_furigana": "と。"
    },
    {
        "id": "f000125",
        "sentence": "なお床下通り二十九番地ポ氏は、",
        "sentence_with_furigana": "なお床下通り二十九番地ポ氏は、"
    },
    {
        "id": "f000126",
        "sentence": "昨夜深更より今朝にかけて、",
        "sentence_with_furigana": "昨夜深更より今朝にかけて、"
    },
    {
        "id": "f000127",
        "sentence": "ツェ氏並びにはりがねせい、",
        "sentence_with_furigana": "ツェ氏並びにはりがねせい、"
    },
    {
        "id": "f000128",
        "sentence": "ねずみとり氏の激しき争論、",
        "sentence_with_furigana": "ねずみとり氏の激しき争論、"
    },
    {
        "id": "f000129",
        "sentence": "時に格闘の声を聞きたりと。",
        "sentence_with_furigana": "時に格闘の声を聞きたりと。"
    },
    {
        "id": "f000130",
        "sentence": "以上を総合するに、",
        "sentence_with_furigana": "以上を総合するに、"
    },
    {
        "id": "f000131",
        "sentence": "本事件には、",
        "sentence_with_furigana": "本事件には、"
    },
    {
        "id": "f000132",
        "sentence": "はりがねせい、",
        "sentence_with_furigana": "はりがねせい、"
    },
    {
        "id": "f000133",
        "sentence": "ねずみとり氏、",
        "sentence_with_furigana": "ねずみとり氏、"
    },
    {
        "id": "f000134",
        "sentence": "最も深き関係を有するがごとし。",
        "sentence_with_furigana": "最も深き関係を有するがごとし。"
    },
    {
        "id": "f000135",
        "sentence": "本社はさらに深く事件の真相を探知の上、",
        "sentence_with_furigana": "本社はさらに深く事件の真相を探知の上、"
    },
    {
        "id": "f000136",
        "sentence": "大いにはりがねせい、",
        "sentence_with_furigana": "大いにはりがねせい、"
    },
    {
        "id": "f000137",
        "sentence": "ねずみとり氏に筆誅を加えんと欲す。",
        "sentence_with_furigana": "ねずみとり氏に 筆誅[ひっちゅう]を加えんと欲す。"
    },
    {
        "id": "f000138",
        "sentence": "と。ははは、",
        "sentence_with_furigana": "と。ははは、"
    },
    {
        "id": "f000139",
        "sentence": "ふん、",
        "sentence_with_furigana": "ふん、"
    },
    {
        "id": "f000140",
        "sentence": "これはもう疑いもない。",
        "sentence_with_furigana": "これはもう疑いもない。"
    },
    {
        "id": "f000141",
        "sentence": "ツェのやつめ、",
        "sentence_with_furigana": "ツェのやつめ、"
    },
    {
        "id": "f000142",
        "sentence": "ねずみとりに食われたんだ。",
        "sentence_with_furigana": "ねずみとりに食われたんだ。"
    },
    {
        "id": "f000143",
        "sentence": "おもしろい。",
        "sentence_with_furigana": "おもしろい。"
    },
    {
        "id": "f000144",
        "sentence": "そのつぎはと。",
        "sentence_with_furigana": "そのつぎはと。"
    },
    {
        "id": "f000145",
        "sentence": "なんだ、",
        "sentence_with_furigana": "なんだ、"
    },
    {
        "id": "f000146",
        "sentence": "ええと、",
        "sentence_with_furigana": "ええと、"
    },
    {
        "id": "f000147",
        "sentence": "新任ねずみ会議員テ氏。",
        "sentence_with_furigana": "新任ねずみ会議員テ氏。"
    },
    {
        "id": "f000148",
        "sentence": "エヘン、",
        "sentence_with_furigana": "エヘン、"
    },
    {
        "id": "f000149",
        "sentence": "エヘン。",
        "sentence_with_furigana": "エヘン。"
    },
    {
        "id": "f000150",
        "sentence": "エン。",
        "sentence_with_furigana": "エン。"
    },
    {
        "id": "f000151",
        "sentence": "エッヘン。",
        "sentence_with_furigana": "エッヘン。"
    },
    {
        "id": "f000152",
        "sentence": "ヴェイヴェイ。",
        "sentence_with_furigana": "ヴェイヴェイ。"
    },
    {
        "id": "f000153",
        "sentence": "なんだちくしょう。",
        "sentence_with_furigana": "なんだちくしょう。"
    },
    {
        "id": "f000154",
        "sentence": "テなどがねずみ会議員だなんて。",
        "sentence_with_furigana": "テなどがねずみ会議員だなんて。"
    },
    {
        "id": "f000155",
        "sentence": "えい、",
        "sentence_with_furigana": "えい、"
    },
    {
        "id": "f000156",
        "sentence": "おもしろくない。",
        "sentence_with_furigana": "おもしろくない。"
    },
    {
        "id": "f000157",
        "sentence": "おれでもすればいいんだ。",
        "sentence_with_furigana": "おれでもすればいいんだ。"
    },
    {
        "id": "f000158",
        "sentence": "えい。",
        "sentence_with_furigana": "えい。"
    },
    {
        "id": "f000159",
        "sentence": "おもしろくもない、",
        "sentence_with_furigana": "おもしろくもない、"
    },
    {
        "id": "f000160",
        "sentence": "散歩に出よう。」",
        "sentence_with_furigana": "散歩に出よう。」"
    },
    {
        "id": "f000161",
        "sentence": "そこでクねずみは散歩に出ました。",
        "sentence_with_furigana": "そこでクねずみは散歩に出ました。"
    },
    {
        "id": "f000162",
        "sentence": "そしてプンプンおこりながら、",
        "sentence_with_furigana": "そしてプンプンおこりながら、"
    },
    {
        "id": "f000163",
        "sentence": "天井裏街の方へ行く途中で、",
        "sentence_with_furigana": "天井裏街の方へ行く途中で、"
    },
    {
        "id": "f000164",
        "sentence": "二匹のむかでが親孝行の蜘蛛の話をしているのを聞きました。",
        "sentence_with_furigana": "二匹のむかでが親孝行の 蜘蛛[くも]の話をしているのを聞きました。"
    },
    {
        "id": "f000165",
        "sentence": "「ほんとうにね、",
        "sentence_with_furigana": "「ほんとうにね、"
    },
    {
        "id": "f000166",
        "sentence": "そうはできないもんだよ。」",
        "sentence_with_furigana": "そうはできないもんだよ。」"
    },
    {
        "id": "f000167",
        "sentence": "「ええ、",
        "sentence_with_furigana": "「ええ、"
    },
    {
        "id": "f000168",
        "sentence": "ええ、",
        "sentence_with_furigana": "ええ、"
    },
    {
        "id": "f000169",
        "sentence": "全くですよ。",
        "sentence_with_furigana": "全くですよ。"
    },
    {
        "id": "f000170",
        "sentence": "",
        "sentence_with_furigana": ""
    },
    {
        "id": "f000171",
        "sentence": "それにあの子は、",
        "sentence_with_furigana": "それにあの子は、"
    },
    {
        "id": "f000172",
        "sentence": "自分もどこかからだが悪いんですよ。",
        "sentence_with_furigana": "自分もどこかからだが悪いんですよ。"
    },
    {
        "id": "f000173",
        "sentence": "それだのにね、",
        "sentence_with_furigana": "それだのにね、"
    },
    {
        "id": "f000174",
        "sentence": "朝は二時ごろから起きて薬を飲ませたり、",
        "sentence_with_furigana": "朝は二時ごろから起きて薬を飲ませたり、"
    },
    {
        "id": "f000175",
        "sentence": "おかゆをたいてやったり、",
        "sentence_with_furigana": "おかゆをたいてやったり、"
    },
    {
        "id": "f000176",
        "sentence": "夜だって寝るのはいつもおそいでしょう。",
        "sentence_with_furigana": "夜だって寝るのはいつもおそいでしょう。"
    },
    {
        "id": "f000177",
        "sentence": "たいてい三時ごろでしょう。",
        "sentence_with_furigana": "たいてい三時ごろでしょう。"
    },
    {
        "id": "f000178",
        "sentence": "ほんとうにからだがやすまるってないんでしょう。",
        "sentence_with_furigana": "ほんとうにからだがやすまるってないんでしょう。"
    },
    {
        "id": "f000179",
        "sentence": "感心ですねえ。」",
        "sentence_with_furigana": "感心ですねえ。」"
    },
    {
        "id": "f000180",
        "sentence": "「ほんとうにあんな心がけのいい子は今ごろあり……。」",
        "sentence_with_furigana": "「ほんとうにあんな心がけのいい子は今ごろあり……。」"
    },
    {
        "id": "f000181",
        "sentence": "「エヘン、",
        "sentence_with_furigana": "「エヘン、"
    },
    {
        "id": "f000182",
        "sentence": "エヘン。",
        "sentence_with_furigana": "エヘン。"
    },
    {
        "id": "f000183",
        "sentence": "」と、",
        "sentence_with_furigana": "」と、"
    },
    {
        "id": "f000184",
        "sentence": "いきなりクねずみはどなって、",
        "sentence_with_furigana": "いきなりクねずみはどなって、"
    },
    {
        "id": "f000185",
        "sentence": "おひげを横の方へひっぱりました。",
        "sentence_with_furigana": "おひげを横の方へひっぱりました。"
    },
    {
        "id": "f000186",
        "sentence": "むかではびっくりして、",
        "sentence_with_furigana": "むかではびっくりして、"
    },
    {
        "id": "f000187",
        "sentence": "はなしもなにもそこそこに別れて逃げて行ってしまいました。",
        "sentence_with_furigana": "はなしもなにもそこそこに別れて逃げて行ってしまいました。"
    },
    {
        "id": "f000188",
        "sentence": "クねずみはそれからだんだん天井裏街の方へのぼって行きました。",
        "sentence_with_furigana": "クねずみはそれからだんだん天井裏街の方へのぼって行きました。"
    },
    {
        "id": "f000189",
        "sentence": "天井裏街のガランとした広い通りでは、",
        "sentence_with_furigana": "天井裏街のガランとした広い通りでは、"
    },
    {
        "id": "f000190",
        "sentence": "ねずみ会議員のテねずみがもう一ぴきのねずみとはなしていました。",
        "sentence_with_furigana": "ねずみ会議員のテねずみがもう一ぴきのねずみとはなしていました。"
    },
    {
        "id": "f000191",
        "sentence": "クねずみはこわれたちり取りのかげで立ちぎきをしておりました。",
        "sentence_with_furigana": "クねずみはこわれたちり取りのかげで立ちぎきをしておりました。"
    },
    {
        "id": "f000192",
        "sentence": "テねずみが、",
        "sentence_with_furigana": "テねずみが、"
    },
    {
        "id": "f000193",
        "sentence": "「それで、",
        "sentence_with_furigana": "「それで、"
    },
    {
        "id": "f000194",
        "sentence": "その、",
        "sentence_with_furigana": "その、"
    },
    {
        "id": "f000195",
        "sentence": "わたしの考えではね、",
        "sentence_with_furigana": "わたしの考えではね、"
    },
    {
        "id": "f000196",
        "sentence": "どうしてもこれは、",
        "sentence_with_furigana": "どうしてもこれは、"
    },
    {
        "id": "f000197",
        "sentence": "その、",
        "sentence_with_furigana": "その、"
    },
    {
        "id": "f000198",
        "sentence": "共同一致、",
        "sentence_with_furigana": "共同一致、"
    },
    {
        "id": "f000199",
        "sentence": "団結、",
        "sentence_with_furigana": "団結、"
    },
    {
        "id": "f000200",
        "sentence": "和睦の、",
        "sentence_with_furigana": "和睦[わぼく]の、"
    },
    {
        "id": "f000201",
        "sentence": "セイシンで、",
        "sentence_with_furigana": "セイシンで、"
    },
    {
        "id": "f000202",
        "sentence": "やらんと、",
        "sentence_with_furigana": "やらんと、"
    },
    {
        "id": "f000203",
        "sentence": "いかんね。",
        "sentence_with_furigana": "いかんね。"
    },
    {
        "id": "f000204",
        "sentence": "」と言いました。",
        "sentence_with_furigana": "」と言いました。"
    },
    {
        "id": "f000205",
        "sentence": "クねずみは、",
        "sentence_with_furigana": "クねずみは、"
    },
    {
        "id": "f000206",
        "sentence": "「エヘン、",
        "sentence_with_furigana": "「エヘン、"
    },
    {
        "id": "f000207",
        "sentence": "エヘン。",
        "sentence_with_furigana": "エヘン。"
    },
    {
        "id": "f000208",
        "sentence": "」と聞こえないようにせきばらいをしました。",
        "sentence_with_furigana": "」と聞こえないようにせきばらいをしました。"
    },
    {
        "id": "f000209",
        "sentence": "相手のねずみは、",
        "sentence_with_furigana": "相手のねずみは、"
    },
    {
        "id": "f000210",
        "sentence": "「へい。",
        "sentence_with_furigana": "「へい。"
    },
    {
        "id": "f000211",
        "sentence": "」と言って考えているようです。",
        "sentence_with_furigana": "」と言って考えているようです。"
    },
    {
        "id": "f000212",
        "sentence": "テねずみははなしをつづけました。",
        "sentence_with_furigana": "テねずみははなしをつづけました。"
    },
    {
        "id": "f000213",
        "sentence": "「もしそうでないとすると、",
        "sentence_with_furigana": "「もしそうでないとすると、"
    },
    {
        "id": "f000214",
        "sentence": "つまりその、",
        "sentence_with_furigana": "つまりその、"
    },
    {
        "id": "f000215",
        "sentence": "世界のシンポハッタツ、",
        "sentence_with_furigana": "世界のシンポハッタツ、"
    },
    {
        "id": "f000216",
        "sentence": "カイゼンカイリョウがそのつまりテイタイするね。」",
        "sentence_with_furigana": "カイゼンカイリョウがそのつまりテイタイするね。」"
    },
    {
        "id": "f000217",
        "sentence": "「エン、",
        "sentence_with_furigana": "「エン、"
    },
    {
        "id": "f000218",
        "sentence": "エン、",
        "sentence_with_furigana": "エン、"
    },
    {
        "id": "f000219",
        "sentence": "エイ、",
        "sentence_with_furigana": "エイ、"
    },
    {
        "id": "f000220",
        "sentence": "エイ。",
        "sentence_with_furigana": "エイ。"
    },
    {
        "id": "f000221",
        "sentence": "」クねずみはまたひくくせきばらいをしました。",
        "sentence_with_furigana": "」クねずみはまたひくくせきばらいをしました。"
    },
    {
        "id": "f000222",
        "sentence": "相手のねずみは、",
        "sentence_with_furigana": "相手のねずみは、"
    },
    {
        "id": "f000223",
        "sentence": "「へい。",
        "sentence_with_furigana": "「へい。"
    },
    {
        "id": "f000224",
        "sentence": "」と言って考えています。",
        "sentence_with_furigana": "」と言って考えています。"
    },
    {
        "id": "f000225",
        "sentence": "「そこで、",
        "sentence_with_furigana": "「そこで、"
    },
    {
        "id": "f000226",
        "sentence": "その、",
        "sentence_with_furigana": "その、"
    },
    {
        "id": "f000227",
        "sentence": "世界文明のシンポハッタツ、",
        "sentence_with_furigana": "世界文明のシンポハッタツ、"
    },
    {
        "id": "f000228",
        "sentence": "カイリョウカイゼンがテイタイすると、",
        "sentence_with_furigana": "カイリョウカイゼンがテイタイすると、"
    },
    {
        "id": "f000229",
        "sentence": "政治はもちろんケイザイ、",
        "sentence_with_furigana": "政治はもちろんケイザイ、"
    },
    {
        "id": "f000230",
        "sentence": "ノウギョウ、",
        "sentence_with_furigana": "ノウギョウ、"
    },
    {
        "id": "f000231",
        "sentence": "ジツギョウ、",
        "sentence_with_furigana": "ジツギョウ、"
    },
    {
        "id": "f000232",
        "sentence": "コウギョウ、",
        "sentence_with_furigana": "コウギョウ、"
    },
    {
        "id": "f000233",
        "sentence": "キョウイク、",
        "sentence_with_furigana": "キョウイク、"
    },
    {
        "id": "f000234",
        "sentence": "ビジュツそれからチョウコク、",
        "sentence_with_furigana": "ビジュツそれからチョウコク、"
    },
    {
        "id": "f000235",
        "sentence": "カイガ、",
        "sentence_with_furigana": "カイガ、"
    },
    {
        "id": "f000236",
        "sentence": "それからブンガク、",
        "sentence_with_furigana": "それからブンガク、"
    },
    {
        "id": "f000237",
        "sentence": "シバイ、",
        "sentence_with_furigana": "シバイ、"
    },
    {
        "id": "f000238",
        "sentence": "ええと、",
        "sentence_with_furigana": "ええと、"
    },
    {
        "id": "f000239",
        "sentence": "エンゲキ、",
        "sentence_with_furigana": "エンゲキ、"
    },
    {
        "id": "f000240",
        "sentence": "ゲイジュツ、",
        "sentence_with_furigana": "ゲイジュツ、"
    },
    {
        "id": "f000241",
        "sentence": "ゴラク、",
        "sentence_with_furigana": "ゴラク、"
    },
    {
        "id": "f000242",
        "sentence": "そのほかタイイクなどが、",
        "sentence_with_furigana": "そのほかタイイクなどが、"
    },
    {
        "id": "f000243",
        "sentence": "ハッハッハ、",
        "sentence_with_furigana": "ハッハッハ、"
    },
    {
        "id": "f000244",
        "sentence": "たいへんそのどうもわるくなるね。",
        "sentence_with_furigana": "たいへんそのどうもわるくなるね。"
    },
    {
        "id": "f000245",
        "sentence": "」テねずみはむつかしいことをあまりたくさん言ったので、",
        "sentence_with_furigana": "」テねずみはむつかしいことをあまりたくさん言ったので、"
    },
    {
        "id": "f000246",
        "sentence": "もう愉快でたまらないようでした。",
        "sentence_with_furigana": "もう愉快でたまらないようでした。"
    },
    {
        "id": "f000247",
        "sentence": "クねずみはそれがまたむやみにしゃくにさわって、",
        "sentence_with_furigana": "クねずみはそれがまたむやみにしゃくにさわって、"
    },
    {
        "id": "f000248",
        "sentence": "「エン、",
        "sentence_with_furigana": "「エン、"
    },
    {
        "id": "f000249",
        "sentence": "エン。",
        "sentence_with_furigana": "エン。"
    },
    {
        "id": "f000250",
        "sentence": "」と聞こえないように、",
        "sentence_with_furigana": "」と聞こえないように、"
    },
    {
        "id": "f000251",
        "sentence": "そしてできるだけ高くせきばらいをやって、",
        "sentence_with_furigana": "そしてできるだけ高くせきばらいをやって、"
    },
    {
        "id": "f000252",
        "sentence": "にぎりこぶしをかためました。",
        "sentence_with_furigana": "にぎりこぶしをかためました。"
    },
    {
        "id": "f000253",
        "sentence": "相手のねずみはやはり「へい。",
        "sentence_with_furigana": "相手のねずみはやはり「へい。"
    },
    {
        "id": "f000254",
        "sentence": "」と言っております。",
        "sentence_with_furigana": "」と言っております。"
    },
    {
        "id": "f000255",
        "sentence": "テねずみはまたはじめました。",
        "sentence_with_furigana": "テねずみはまたはじめました。"
    },
    {
        "id": "f000256",
        "sentence": "「そこでそのケイザイやゴラクが悪くなるというと、",
        "sentence_with_furigana": "「そこでそのケイザイやゴラクが悪くなるというと、"
    },
    {
        "id": "f000257",
        "sentence": "不平を生じてブンレツを起こすというケッカにホウチャクするね。",
        "sentence_with_furigana": "不平を生じてブンレツを起こすというケッカにホウチャクするね。"
    },
    {
        "id": "f000258",
        "sentence": "そうなるのは実にそのわれわれのシンガイでフホンイであるから、",
        "sentence_with_furigana": "そうなるのは実にそのわれわれのシンガイでフホンイであるから、"
    },
    {
        "id": "f000259",
        "sentence": "やはりその、",
        "sentence_with_furigana": "やはりその、"
    },
    {
        "id": "f000260",
        "sentence": "ものごとは共同一致団結和睦のセイシンでやらんといかんね。」",
        "sentence_with_furigana": "ものごとは共同一致団結和睦のセイシンでやらんといかんね。」"
    },
    {
        "id": "f000261",
        "sentence": "クねずみはあんまりテねずみのことばが立派で、",
        "sentence_with_furigana": "クねずみはあんまりテねずみのことばが立派で、"
    },
    {
        "id": "f000262",
        "sentence": "議論がうまくできているのがしゃくにさわって、",
        "sentence_with_furigana": "議論がうまくできているのがしゃくにさわって、"
    },
    {
        "id": "f000263",
        "sentence": "とうとうあらんかぎり、",
        "sentence_with_furigana": "とうとうあらんかぎり、"
    },
    {
        "id": "f000264",
        "sentence": "「エヘン、",
        "sentence_with_furigana": "「エヘン、"
    },
    {
        "id": "f000265",
        "sentence": "エヘン。",
        "sentence_with_furigana": "エヘン。"
    },
    {
        "id": "f000266",
        "sentence": "」とやってしまいました。",
        "sentence_with_furigana": "」とやってしまいました。"
    },
    {
        "id": "f000267",
        "sentence": "するとテねずみはぶるるっとふるえて、",
        "sentence_with_furigana": "するとテねずみはぶるるっとふるえて、"
    },
    {
        "id": "f000268",
        "sentence": "目を閉じて、",
        "sentence_with_furigana": "目を閉じて、"
    },
    {
        "id": "f000269",
        "sentence": "小さく小さくちぢまりましたが、",
        "sentence_with_furigana": "小さく小さくちぢまりましたが、"
    },
    {
        "id": "f000270",
        "sentence": "だんだんそろりそろりと延びて、",
        "sentence_with_furigana": "だんだんそろりそろりと延びて、"
    },
    {
        "id": "f000271",
        "sentence": "そおっと目をあいて、",
        "sentence_with_furigana": "そおっと目をあいて、"
    },
    {
        "id": "f000272",
        "sentence": "それから大声で叫びました。",
        "sentence_with_furigana": "それから大声で叫びました。"
    },
    {
        "id": "f000273",
        "sentence": "「こいつは、",
        "sentence_with_furigana": "「こいつは、"
    },
    {
        "id": "f000274",
        "sentence": "ブンレツだぞ。",
        "sentence_with_furigana": "ブンレツだぞ。"
    },
    {
        "id": "f000275",
        "sentence": "ブンレツ者だ。",
        "sentence_with_furigana": "ブンレツ者だ。"
    },
    {
        "id": "f000276",
        "sentence": "しばれ、",
        "sentence_with_furigana": "しばれ、"
    },
    {
        "id": "f000277",
        "sentence": "しばれ。",
        "sentence_with_furigana": "しばれ。"
    },
    {
        "id": "f000278",
        "sentence": "」と叫びました。",
        "sentence_with_furigana": "」と叫びました。"
    },
    {
        "id": "f000279",
        "sentence": "すると相手のねずみは、",
        "sentence_with_furigana": "すると相手のねずみは、"
    },
    {
        "id": "f000280",
        "sentence": "まるでつぶてのようにクねずみに飛びかかってねずみの捕り繩を出して、",
        "sentence_with_furigana": "まるでつぶてのようにクねずみに飛びかかってねずみの 捕[と]り 繩[なわ]を出して、"
    },
    {
        "id": "f000281",
        "sentence": "クルクルしばってしまいました。",
        "sentence_with_furigana": "クルクルしばってしまいました。"
    },
    {
        "id": "f000282",
        "sentence": "クねずみはくやしくてくやしくてなみだが出ましたが、",
        "sentence_with_furigana": "クねずみはくやしくてくやしくてなみだが出ましたが、"
    },
    {
        "id": "f000283",
        "sentence": "どうしてもかないそうがありませんでしたから、",
        "sentence_with_furigana": "どうしてもかないそうがありませんでしたから、"
    },
    {
        "id": "f000284",
        "sentence": "しばらくじっとしておりました。",
        "sentence_with_furigana": "しばらくじっとしておりました。"
    },
    {
        "id": "f000285",
        "sentence": "するとテねずみは紙切れを出してするするするっと何か書いて捕り手のねずみに渡しました。",
        "sentence_with_furigana": "するとテねずみは紙切れを出してするするするっと何か書いて捕り手のねずみに渡しました。"
    },
    {
        "id": "f000286",
        "sentence": "捕り手のねずみは、",
        "sentence_with_furigana": "捕り手のねずみは、"
    },
    {
        "id": "f000287",
        "sentence": "しばられてごろごろころがっているクねずみの前に来て、",
        "sentence_with_furigana": "しばられてごろごろころがっているクねずみの前に来て、"
    },
    {
        "id": "f000288",
        "sentence": "すてきにおごそかな声でそれを読みはじめました。",
        "sentence_with_furigana": "すてきにおごそかな声でそれを読みはじめました。"
    },
    {
        "id": "f000289",
        "sentence": "「クねずみはブンレツ者によりて、",
        "sentence_with_furigana": "「クねずみはブンレツ者によりて、"
    },
    {
        "id": "f000290",
        "sentence": "みんなの前にて暗殺すべし。",
        "sentence_with_furigana": "みんなの前にて暗殺すべし。"
    },
    {
        "id": "f000291",
        "sentence": "」クねずみは声をあげてチュウチュウ泣きました。",
        "sentence_with_furigana": "」クねずみは声をあげてチュウチュウ泣きました。"
    },
    {
        "id": "f000292",
        "sentence": "「さあ、",
        "sentence_with_furigana": "「さあ、"
    },
    {
        "id": "f000293",
        "sentence": "ブンレツ者。",
        "sentence_with_furigana": "ブンレツ者。"
    },
    {
        "id": "f000294",
        "sentence": "あるけ、",
        "sentence_with_furigana": "あるけ、"
    },
    {
        "id": "f000295",
        "sentence": "早く。",
        "sentence_with_furigana": "早く。"
    },
    {
        "id": "f000296",
        "sentence": "」と、",
        "sentence_with_furigana": "」と、"
    },
    {
        "id": "f000297",
        "sentence": "捕り手のねずみは言いました。",
        "sentence_with_furigana": "捕り手のねずみは言いました。"
    },
    {
        "id": "f000298",
        "sentence": "さあ、",
        "sentence_with_furigana": "さあ、"
    },
    {
        "id": "f000299",
        "sentence": "そこでクねずみはすっかり恐れ入ってしおしおと立ちあがりました。",
        "sentence_with_furigana": "そこでクねずみはすっかり恐れ入ってしおしおと立ちあがりました。"
    },
    {
        "id": "f000300",
        "sentence": "あっちからもこっちからもねずみがみんな集まって来て、",
        "sentence_with_furigana": "あっちからもこっちからもねずみがみんな集まって来て、"
    },
    {
        "id": "f000301",
        "sentence": "「どうもいい気味だね。",
        "sentence_with_furigana": "「どうもいい気味だね。"
    },
    {
        "id": "f000302",
        "sentence": "いつでもエヘンエヘンと言ってばかりいたやつなんだ。」",
        "sentence_with_furigana": "いつでもエヘンエヘンと言ってばかりいたやつなんだ。」"
    },
    {
        "id": "f000303",
        "sentence": "「やっぱり分裂していたんだ。」",
        "sentence_with_furigana": "「やっぱり分裂していたんだ。」"
    },
    {
        "id": "f000304",
        "sentence": "「あいつが死んだらほんとうにせいせいするだろうね。",
        "sentence_with_furigana": "「あいつが死んだらほんとうにせいせいするだろうね。"
    },
    {
        "id": "f000305",
        "sentence": "」というような声ばかりです。",
        "sentence_with_furigana": "」というような声ばかりです。"
    },
    {
        "id": "f000306",
        "sentence": "捕り手のねずみは、",
        "sentence_with_furigana": "捕り手のねずみは、"
    },
    {
        "id": "f000307",
        "sentence": "いよいよ白いたすきをかけて、",
        "sentence_with_furigana": "いよいよ白いたすきをかけて、"
    },
    {
        "id": "f000308",
        "sentence": "暗殺のしたくをはじめました。",
        "sentence_with_furigana": "暗殺のしたくをはじめました。"
    },
    {
        "id": "f000309",
        "sentence": "その時みんなのうしろの方で、",
        "sentence_with_furigana": "その時みんなのうしろの方で、"
    },
    {
        "id": "f000310",
        "sentence": "フウフウと言うひどい音が聞こえ、",
        "sentence_with_furigana": "フウフウと言うひどい音が聞こえ、"
    },
    {
        "id": "f000311",
        "sentence": "二つの目玉が火のように光って来ました。",
        "sentence_with_furigana": "二つの目玉が火のように光って来ました。"
    },
    {
        "id": "f000312",
        "sentence": "それは例の猫大将でした。",
        "sentence_with_furigana": "それは例の 猫大将[ねこたいしょう]でした。"
    },
    {
        "id": "f000313",
        "sentence": "「ワーッ。",
        "sentence_with_furigana": "「ワーッ。"
    },
    {
        "id": "f000314",
        "sentence": "」とねずみはみんなちりぢり四方に逃げました。",
        "sentence_with_furigana": "」とねずみはみんなちりぢり四方に逃げました。"
    },
    {
        "id": "f000315",
        "sentence": "「逃がさんぞ。",
        "sentence_with_furigana": "「逃がさんぞ。"
    },
    {
        "id": "f000316",
        "sentence": "コラッ。",
        "sentence_with_furigana": "コラッ。"
    },
    {
        "id": "f000317",
        "sentence": "」と猫大将はその一匹を追いかけましたが、",
        "sentence_with_furigana": "」と猫大将はその一匹を追いかけましたが、"
    },
    {
        "id": "f000318",
        "sentence": "もうせまいすきまへずうっと深くもぐり込んでしまったので、",
        "sentence_with_furigana": "もうせまいすきまへずうっと深くもぐり込んでしまったので、"
    },
    {
        "id": "f000319",
        "sentence": "いくら猫大将が手をのばしてもとどきませんでした。",
        "sentence_with_furigana": "いくら猫大将が手をのばしてもとどきませんでした。"
    },
    {
        "id": "f000320",
        "sentence": "猫大将は「チェッ。",
        "sentence_with_furigana": "猫大将は「チェッ。"
    },
    {
        "id": "f000321",
        "sentence": "」と舌打ちをして戻って来ましたが、",
        "sentence_with_furigana": "」と舌打ちをして戻って来ましたが、"
    },
    {
        "id": "f000322",
        "sentence": "クねずみのただ一匹しばられて残っているのを見て、",
        "sentence_with_furigana": "クねずみのただ一匹しばられて残っているのを見て、"
    },
    {
        "id": "f000323",
        "sentence": "びっくりして言いました。",
        "sentence_with_furigana": "びっくりして言いました。"
    },
    {
        "id": "f000324",
        "sentence": "「貴様はなんと言うものだ。",
        "sentence_with_furigana": "「貴様はなんと言うものだ。"
    },
    {
        "id": "f000325",
        "sentence": "」クねずみはもう落ち着いて答えました。",
        "sentence_with_furigana": "」クねずみはもう落ち着いて答えました。"
    },
    {
        "id": "f000326",
        "sentence": "「クと申します。」",
        "sentence_with_furigana": "「クと申します。」"
    },
    {
        "id": "f000327",
        "sentence": "「フ、",
        "sentence_with_furigana": "「フ、"
    },
    {
        "id": "f000328",
        "sentence": "フ、",
        "sentence_with_furigana": "フ、"
    },
    {
        "id": "f000329",
        "sentence": "そうか、",
        "sentence_with_furigana": "そうか、"
    },
    {
        "id": "f000330",
        "sentence": "なぜこんなにしているんだ。」",
        "sentence_with_furigana": "なぜこんなにしているんだ。」"
    },
    {
        "id": "f000331",
        "sentence": "「暗殺されるためです。」",
        "sentence_with_furigana": "「暗殺されるためです。」"
    },
    {
        "id": "f000332",
        "sentence": "「フ、",
        "sentence_with_furigana": "「フ、"
    },
    {
        "id": "f000333",
        "sentence": "フ、",
        "sentence_with_furigana": "フ、"
    },
    {
        "id": "f000334",
        "sentence": "フ。",
        "sentence_with_furigana": "フ。"
    },
    {
        "id": "f000335",
        "sentence": "そうか。",
        "sentence_with_furigana": "そうか。"
    },
    {
        "id": "f000336",
        "sentence": "それはかあいそうだ。",
        "sentence_with_furigana": "それはかあいそうだ。"
    },
    {
        "id": "f000337",
        "sentence": "よしよし、",
        "sentence_with_furigana": "よしよし、"
    },
    {
        "id": "f000338",
        "sentence": "おれが引き受けてやろう。",
        "sentence_with_furigana": "おれが引き受けてやろう。"
    },
    {
        "id": "f000339",
        "sentence": "おれのうちへ来い。",
        "sentence_with_furigana": "おれのうちへ来い。"
    },
    {
        "id": "f000340",
        "sentence": "ちょうどおれのうちでは、",
        "sentence_with_furigana": "ちょうどおれのうちでは、"
    },
    {
        "id": "f000341",
        "sentence": "子供が四人できて、",
        "sentence_with_furigana": "子供が四人できて、"
    },
    {
        "id": "f000342",
        "sentence": "それに家庭教師がなくて困っているところなんだ。",
        "sentence_with_furigana": "それに家庭教師がなくて困っているところなんだ。"
    },
    {
        "id": "f000343",
        "sentence": "来い。」",
        "sentence_with_furigana": "来い。」"
    },
    {
        "id": "f000344",
        "sentence": "猫大将はのそのそ歩きだしました。",
        "sentence_with_furigana": "猫大将はのそのそ歩きだしました。"
    },
    {
        "id": "f000345",
        "sentence": "クねずみはこわごわあとについて行きました。",
        "sentence_with_furigana": "クねずみはこわごわあとについて行きました。"
    },
    {
        "id": "f000346",
        "sentence": "猫のおうちはどうもそれは立派なもんでした。",
        "sentence_with_furigana": "猫のおうちはどうもそれは立派なもんでした。"
    },
    {
        "id": "f000347",
        "sentence": "紫色の竹で編んであって中はわらや布きれでホクホクしていました。",
        "sentence_with_furigana": "紫色の竹で編んであって中はわらや布きれでホクホクしていました。"
    },
    {
        "id": "f000348",
        "sentence": "おまけにちゃあんとご飯を入れる道具さえあったのです。",
        "sentence_with_furigana": "おまけにちゃあんとご飯を入れる道具さえあったのです。"
    },
    {
        "id": "f000349",
        "sentence": "そしてその中に、",
        "sentence_with_furigana": "そしてその中に、"
    },
    {
        "id": "f000350",
        "sentence": "猫大将の子供が四人、",
        "sentence_with_furigana": "猫大将[ねこたいしょう]の子供が四人、"
    },
    {
        "id": "f000351",
        "sentence": "やっと目をあいて、",
        "sentence_with_furigana": "やっと目をあいて、"
    },
    {
        "id": "f000352",
        "sentence": "にゃあにゃあと鳴いておりました。",
        "sentence_with_furigana": "にゃあにゃあと鳴いておりました。"
    },
    {
        "id": "f000353",
        "sentence": "猫大将は子供らを一つずつなめてやってから言いました。",
        "sentence_with_furigana": "猫大将は子供らを一つずつなめてやってから言いました。"
    },
    {
        "id": "f000354",
        "sentence": "「お前たちはもう学問をしないといけない。",
        "sentence_with_furigana": "「お前たちはもう学問をしないといけない。"
    },
    {
        "id": "f000355",
        "sentence": "ここへ先生をたのんで来たからな。",
        "sentence_with_furigana": "ここへ先生をたのんで来たからな。"
    },
    {
        "id": "f000356",
        "sentence": "よく習うんだよ。",
        "sentence_with_furigana": "よく習うんだよ。"
    },
    {
        "id": "f000357",
        "sentence": "決して先生を食べてしまったりしてはいかんぞ。」",
        "sentence_with_furigana": "決して先生を食べてしまったりしてはいかんぞ。」"
    },
    {
        "id": "f000358",
        "sentence": "子供らはよろこんでニヤニヤ笑って口々に、",
        "sentence_with_furigana": "子供らはよろこんでニヤニヤ笑って口々に、"
    },
    {
        "id": "f000359",
        "sentence": "「おとうさん、",
        "sentence_with_furigana": "「おとうさん、"
    },
    {
        "id": "f000360",
        "sentence": "ありがとう。",
        "sentence_with_furigana": "ありがとう。"
    },
    {
        "id": "f000361",
        "sentence": "きっと習うよ。",
        "sentence_with_furigana": "きっと習うよ。"
    },
    {
        "id": "f000362",
        "sentence": "先生を食べてしまったりしないよ。",
        "sentence_with_furigana": "先生を食べてしまったりしないよ。"
    },
    {
        "id": "f000363",
        "sentence": "」と言いました。",
        "sentence_with_furigana": "」と言いました。"
    },
    {
        "id": "f000364",
        "sentence": "クねずみはどうも思わず足がブルブルしました。",
        "sentence_with_furigana": "クねずみはどうも思わず足がブルブルしました。"
    },
    {
        "id": "f000365",
        "sentence": "猫大将が言いました。",
        "sentence_with_furigana": "猫大将が言いました。"
    },
    {
        "id": "f000366",
        "sentence": "「教えてやってくれ。",
        "sentence_with_furigana": "「教えてやってくれ。"
    },
    {
        "id": "f000367",
        "sentence": "おもに算術をな。」",
        "sentence_with_furigana": "おもに算術をな。」"
    },
    {
        "id": "f000368",
        "sentence": "「へい。",
        "sentence_with_furigana": "「へい。"
    },
    {
        "id": "f000369",
        "sentence": "しょう、",
        "sentence_with_furigana": "しょう、"
    },
    {
        "id": "f000370",
        "sentence": "しょう、",
        "sentence_with_furigana": "しょう、"
    },
    {
        "id": "f000371",
        "sentence": "承知いたしました。",
        "sentence_with_furigana": "承知いたしました。"
    },
    {
        "id": "f000372",
        "sentence": "」とクねずみが答えました。",
        "sentence_with_furigana": "」とクねずみが答えました。"
    },
    {
        "id": "f000373",
        "sentence": "猫大将はきげんよくニャーと鳴いてするりと向こうへ行ってしまいました。",
        "sentence_with_furigana": "猫大将はきげんよくニャーと鳴いてするりと向こうへ行ってしまいました。"
    },
    {
        "id": "f000374",
        "sentence": "子供らが叫びました。",
        "sentence_with_furigana": "子供らが叫びました。"
    },
    {
        "id": "f000375",
        "sentence": "「先生、",
        "sentence_with_furigana": "「先生、"
    },
    {
        "id": "f000376",
        "sentence": "早く算術を教えてください。",
        "sentence_with_furigana": "早く算術を教えてください。"
    },
    {
        "id": "f000377",
        "sentence": "先生。",
        "sentence_with_furigana": "先生。"
    },
    {
        "id": "f000378",
        "sentence": "早く。」",
        "sentence_with_furigana": "早く。」"
    },
    {
        "id": "f000379",
        "sentence": "クねずみはさあ、",
        "sentence_with_furigana": "クねずみはさあ、"
    },
    {
        "id": "f000380",
        "sentence": "これはいよいよ教えないといかんと思いましたので、",
        "sentence_with_furigana": "これはいよいよ教えないといかんと思いましたので、"
    },
    {
        "id": "f000381",
        "sentence": "口早に言いました。",
        "sentence_with_furigana": "口早に言いました。"
    },
    {
        "id": "f000382",
        "sentence": "「一に一をたすと二です。」",
        "sentence_with_furigana": "「一に一をたすと二です。」"
    },
    {
        "id": "f000383",
        "sentence": "「そうだよ。",
        "sentence_with_furigana": "「そうだよ。"
    },
    {
        "id": "f000384",
        "sentence": "」子供らが言いました。",
        "sentence_with_furigana": "」子供らが言いました。"
    },
    {
        "id": "f000385",
        "sentence": "「一から一を引くとなんにもなくなります。」",
        "sentence_with_furigana": "「一から一を引くとなんにもなくなります。」"
    },
    {
        "id": "f000386",
        "sentence": "「わかったよ。」",
        "sentence_with_furigana": "「わかったよ。」"
    },
    {
        "id": "f000387",
        "sentence": "子供らが叫びました。",
        "sentence_with_furigana": "子供らが叫びました。"
    },
    {
        "id": "f000388",
        "sentence": "「一に一をかけると一です。」",
        "sentence_with_furigana": "「一に一をかけると一です。」"
    },
    {
        "id": "f000389",
        "sentence": "「きまってるよ。",
        "sentence_with_furigana": "「きまってるよ。"
    },
    {
        "id": "f000390",
        "sentence": "」と猫の子供らが目をりんと張ったまま答えました。",
        "sentence_with_furigana": "」と猫の子供らが目をりんと張ったまま答えました。"
    },
    {
        "id": "f000391",
        "sentence": "「一を一で割ると一です。」",
        "sentence_with_furigana": "「一を一で割ると一です。」"
    },
    {
        "id": "f000392",
        "sentence": "「それでいいよ。",
        "sentence_with_furigana": "「それでいいよ。"
    },
    {
        "id": "f000393",
        "sentence": "」と猫の子供らがよろこんで叫びました。",
        "sentence_with_furigana": "」と猫の子供らがよろこんで叫びました。"
    },
    {
        "id": "f000394",
        "sentence": "そこでクねずみはすっかりのぼせてしまいました。",
        "sentence_with_furigana": "そこでクねずみはすっかりのぼせてしまいました。"
    },
    {
        "id": "f000395",
        "sentence": "「一に二をたすと三です。」",
        "sentence_with_furigana": "「一に二をたすと三です。」"
    },
    {
        "id": "f000396",
        "sentence": "「合ってるよ。」",
        "sentence_with_furigana": "「合ってるよ。」"
    },
    {
        "id": "f000397",
        "sentence": "「一から二を引くと……」と言おうとしてクねずみは、",
        "sentence_with_furigana": "「一から二を引くと……」と言おうとしてクねずみは、"
    },
    {
        "id": "f000398",
        "sentence": "はっとつまってしまいました。",
        "sentence_with_furigana": "はっとつまってしまいました。"
    },
    {
        "id": "f000399",
        "sentence": "すると猫の子供らは一度に叫びました。",
        "sentence_with_furigana": "すると猫の子供らは一度に叫びました。"
    },
    {
        "id": "f000400",
        "sentence": "「一から二は引かれないよ。」",
        "sentence_with_furigana": "「一から二は引かれないよ。」"
    },
    {
        "id": "f000401",
        "sentence": "クねずみはあんまり猫の子供らがかしこいので、",
        "sentence_with_furigana": "クねずみはあんまり猫の子供らがかしこいので、"
    },
    {
        "id": "f000402",
        "sentence": "すっかりむしゃくしゃして、",
        "sentence_with_furigana": "すっかりむしゃくしゃして、"
    },
    {
        "id": "f000403",
        "sentence": "また早口に言いました。",
        "sentence_with_furigana": "また早口に言いました。"
    },
    {
        "id": "f000404",
        "sentence": "そうでしょう。",
        "sentence_with_furigana": "そうでしょう。"
    },
    {
        "id": "f000405",
        "sentence": "クねずみはいちばんはじめの一に一をたして二をおぼえるのに半年かかったのです。",
        "sentence_with_furigana": "クねずみはいちばんはじめの一に一をたして二をおぼえるのに半年かかったのです。"
    },
    {
        "id": "f000406",
        "sentence": "「一に二をかけると二です。」",
        "sentence_with_furigana": "「一に二をかけると二です。」"
    },
    {
        "id": "f000407",
        "sentence": "「そうともさ。」",
        "sentence_with_furigana": "「そうともさ。」"
    },
    {
        "id": "f000408",
        "sentence": "「一を二で割ると……。",
        "sentence_with_furigana": "「一を二で割ると……。"
    },
    {
        "id": "f000409",
        "sentence": "」クねずみはまたつまってしまいました。",
        "sentence_with_furigana": "」クねずみはまたつまってしまいました。"
    },
    {
        "id": "f000410",
        "sentence": "すると猫の子供らはまた一度に声をそろえて、",
        "sentence_with_furigana": "すると猫の子供らはまた一度に声をそろえて、"
    },
    {
        "id": "f000411",
        "sentence": "「一割る二では半分だよ。",
        "sentence_with_furigana": "「一割る二では半分だよ。"
    },
    {
        "id": "f000412",
        "sentence": "」と叫びました。",
        "sentence_with_furigana": "」と叫びました。"
    },
    {
        "id": "f000413",
        "sentence": "クねずみはあんまり猫の子供らの賢いのがしゃくにさわって、",
        "sentence_with_furigana": "クねずみはあんまり 猫[ねこ]の子供らの賢いのがしゃくにさわって、"
    },
    {
        "id": "f000414",
        "sentence": "思わず「エヘン。",
        "sentence_with_furigana": "思わず「エヘン。"
    },
    {
        "id": "f000415",
        "sentence": "エヘン。",
        "sentence_with_furigana": "エヘン。"
    },
    {
        "id": "f000416",
        "sentence": "エイ。",
        "sentence_with_furigana": "エイ。"
    },
    {
        "id": "f000417",
        "sentence": "エイ。」",
        "sentence_with_furigana": "エイ。」"
    },
    {
        "id": "f000418",
        "sentence": "とやりました。",
        "sentence_with_furigana": "とやりました。"
    },
    {
        "id": "f000419",
        "sentence": "すると猫の子供らは、",
        "sentence_with_furigana": "すると猫の子供らは、"
    },
    {
        "id": "f000420",
        "sentence": "しばらくびっくりしたように、",
        "sentence_with_furigana": "しばらくびっくりしたように、"
    },
    {
        "id": "f000421",
        "sentence": "顔を見合わせていましたが、",
        "sentence_with_furigana": "顔を見合わせていましたが、"
    },
    {
        "id": "f000422",
        "sentence": "やがてみんな一度に立ちあがって、",
        "sentence_with_furigana": "やがてみんな一度に立ちあがって、"
    },
    {
        "id": "f000423",
        "sentence": "「なんだい。",
        "sentence_with_furigana": "「なんだい。"
    },
    {
        "id": "f000424",
        "sentence": "ねずめ、",
        "sentence_with_furigana": "ねずめ、"
    },
    {
        "id": "f000425",
        "sentence": "人をそねみやがったな。",
        "sentence_with_furigana": "人をそねみやがったな。"
    },
    {
        "id": "f000426",
        "sentence": "」と言いながらクねずみの足を一ぴきが一つずつかじりました。",
        "sentence_with_furigana": "」と言いながらクねずみの足を一ぴきが一つずつかじりました。"
    },
    {
        "id": "f000427",
        "sentence": "クねずみは非常にあわててばたばたして、",
        "sentence_with_furigana": "クねずみは非常にあわててばたばたして、"
    },
    {
        "id": "f000428",
        "sentence": "急いで「エヘン、",
        "sentence_with_furigana": "急いで「エヘン、"
    },
    {
        "id": "f000429",
        "sentence": "エヘン、",
        "sentence_with_furigana": "エヘン、"
    },
    {
        "id": "f000430",
        "sentence": "エイ、",
        "sentence_with_furigana": "エイ、"
    },
    {
        "id": "f000431",
        "sentence": "エイ。",
        "sentence_with_furigana": "エイ。"
    },
    {
        "id": "f000432",
        "sentence": "」とやりましたがもういけませんでした。",
        "sentence_with_furigana": "」とやりましたがもういけませんでした。"
    },
    {
        "id": "f000433",
        "sentence": "クねずみはだんだん四方の足から食われて行って、",
        "sentence_with_furigana": "クねずみはだんだん四方の足から食われて行って、"
    },
    {
        "id": "f000434",
        "sentence": "とうとうおしまいに四ひきの子猫は、",
        "sentence_with_furigana": "とうとうおしまいに四ひきの子猫は、"
    },
    {
        "id": "f000435",
        "sentence": "クねずみの胃の腑のところで頭をコツンとぶっつけました。",
        "sentence_with_furigana": "クねずみの胃の 腑[ふ]のところで頭をコツンとぶっつけました。"
    },
    {
        "id": "f000436",
        "sentence": "そこへ猫大将が帰って来て、",
        "sentence_with_furigana": "そこへ猫大将が帰って来て、"
    },
    {
        "id": "f000437",
        "sentence": "「何か習ったか。",
        "sentence_with_furigana": "「何か習ったか。"
    },
    {
        "id": "f000438",
        "sentence": "」とききました。",
        "sentence_with_furigana": "」とききました。"
    },
    {
        "id": "f000439",
        "sentence": "「ねずみをとることです。",
        "sentence_with_furigana": "「ねずみをとることです。"
    },
    {
        "id": "f000440",
        "sentence": "」と四ひきがいっしょに答えました。",
        "sentence_with_furigana": "」と四ひきがいっしょに答えました。"
    }
]